{
  "$schema": "./ModuleDoc.schema.json",
  "autoGeneratedHeader": false,
  "name": "process",
  "type": "module",
  "status": "partial",
  "docsUrl": "https://nodejs.org/api/process.html",
  "nodeVersionTarget": "22.x LTS",
  "implementation": [
    "JavaScriptRuntime/Node/Process.cs",
    "JavaScriptRuntime/GlobalVariables.cs"
  ],
  "apis": [
    {
      "name": "argv",
      "kind": "property",
      "status": "supported",
      "notes": "argv[0] normalized to current script filename; extra host args trimmed in tests.",
      "docs": "https://nodejs.org/api/process.html#processargv",
      "tests": [
        {
          "name": "Js2IL.Tests.Node.Process.ExecutionTests.Environment_EnumerateProcessArgV",
          "file": "Js2IL.Tests/Node/Process/ExecutionTests.cs"
        },
        {
          "name": "Js2IL.Tests.Node.Process.GeneratorTests.Environment_EnumerateProcessArgV",
          "file": "Js2IL.Tests/Node/Process/GeneratorTests.cs"
        }
      ]
    },
    {
      "name": "exit()",
      "kind": "function",
      "status": "supported",
      "notes": "Sets the current exitCode on the host environment abstraction without terminating the test host.",
      "docs": "https://nodejs.org/api/process.html#processexitcode",
      "tests": [
        {
          "name": "Js2IL.Tests.Node.Process.ExecutionTests.Process_Exit_Uses_Current_ExitCode",
          "file": "Js2IL.Tests/Node/Process/ExecutionTests.cs"
        }
      ]
    },
    {
      "name": "exit(code)",
      "kind": "function",
      "status": "supported",
      "notes": "Coerces the code to int, sets it on the environment abstraction, and does not terminate the test host.",
      "docs": "https://nodejs.org/api/process.html#process_exit_code",
      "tests": [
        {
          "name": "Js2IL.Tests.Node.Process.ExecutionTests.Process_Exit_Code_Sets_ExitCode",
          "file": "Js2IL.Tests/Node/Process/ExecutionTests.cs"
        }
      ]
    },
    {
      "name": "exitCode",
      "kind": "property",
      "status": "supported",
      "docs": "https://nodejs.org/api/process.html#processexitcode",
      "tests": [
        {
          "name": "Js2IL.Tests.Node.Process.ProcessExitCodeTests.Process_exitCode_getter_setter_mirrors_Environment",
          "file": "Js2IL.Tests/Node/Process/ProcessExitCodeTests.cs"
        }
      ]
    }
  ]
}
